LICENSE.txt
README.rst
requirements.pip
setup.py
django_informant.egg-info/PKG-INFO
django_informant.egg-info/SOURCES.txt
django_informant.egg-info/dependency_links.txt
django_informant.egg-info/requires.txt
django_informant.egg-info/top_level.txt
informant/__init__.py
informant/admin.py
informant/forms.py
informant/models.py
informant/newman_admin.py
informant/process.py
informant/tasks.py
informant/urls.py
informant/views.py
informant/locale/cs/LC_MESSAGES/django.mo
informant/locale/cs/LC_MESSAGES/django.po
informant/management/__init__.py
informant/management/commands/__init__.py
informant/management/commands/send_newsletter.py
informant/migrations/0001_initial.py
informant/migrations/0002_auto__add_field_newsletter_testing_emails.py
informant/migrations/__init__.py
informant/static/js/jquery.informantSubscribeForm.js
informant/templates/informant/mail/base.html
informant/templates/informant/mail/base.txt
informant/templates/informant/mail/newsletter.html
informant/templates/informant/management/subscribe_error.html
informant/templates/informant/management/subscribe_ok.html
informant/templates/informant/management/unsubscribed.html