Metadata-Version: 1.1
Name: django-informant
Version: 1.1.0
Summary: Simple newsletter application for Django framework.
Home-page: UNKNOWN
Author: Fragaria, s.r.o.
Author-email: info@fragaria.cz
License: MIT
Platform: UNKNOWN
Classifier: Development Status :: 5 - Production/Stable
Classifier: Intended Audience :: Developers
Classifier: Operating System :: OS Independent
Classifier: Framework :: Django
Classifier: Programming Language :: Python :: 2.5
Classifier: Programming Language :: Python :: 2.6
Classifier: Programming Language :: Python :: 2.7
Classifier: Topic :: Internet :: WWW/HTTP :: Dynamic Content
Classifier: Topic :: Software Development :: Libraries :: Python Modules
